libexperiment/__init__.py
libexperiment/config.py
libexperiment/experiment.py
libexperiment-1.0.dist-info/LICENSE
libexperiment-1.0.dist-info/METADATA
libexperiment-1.0.dist-info/WHEEL
libexperiment-1.0.dist-info/top_level.txt
libexperiment-1.0.dist-info/zip-safe
libexperiment-1.0.dist-info/RECORD
