Metadata-Version: 2.1
Name: libexperiment
Version: 1.0
Summary: Utilities to perform and re-product experiments.
Home-page: https://github.com/XoriieInpottn/libexperiment
Author: xi
Author-email: gylv@mail.ustc.edu.cn
License: Apache-2.0 license 
Platform: any
Classifier: Programming Language :: Python :: 3.6
Classifier: Programming Language :: Python :: 3.7
Classifier: Programming Language :: Python :: 3.8
License-File: LICENSE
